text_processor_zhangxin/__init__.py
text_processor_zhangxin/processor.py
text_processor_zhangxin-0.1.0.dist-info/LICENSE
text_processor_zhangxin-0.1.0.dist-info/METADATA
text_processor_zhangxin-0.1.0.dist-info/WHEEL
text_processor_zhangxin-0.1.0.dist-info/top_level.txt
text_processor_zhangxin-0.1.0.dist-info/RECORD
