Metadata-Version: 2.1
Name: text_processor_zhangxin
Version: 0.1.0
Summary: A package for advanced text processing tasks by zhangxin
Home-page: https://github.com/your_username/text_processor_zhangxin
Author: Zhang Xin
Author-email: 2931344238@qq.com
Classifier: Programming Language :: Python :: 3
Classifier: License :: OSI Approved :: MIT License
Classifier: Operating System :: OS Independent
Requires-Python: >=3.6
License-File: LICENSE
